mig3_client/__init__.py
mig3_client/errors.py
mig3_client/vendors/__init__.py
mig3_client/vendors/poetry_version.py
mig3_client-0.5.9.dist-info/entry_points.txt
mig3_client-0.5.9.dist-info/LICENSE
mig3_client-0.5.9.dist-info/WHEEL
mig3_client-0.5.9.dist-info/METADATA
mig3_client-0.5.9.dist-info/RECORD
