Metadata-Version: 2.1
Name: mig3-client
Version: 0.5.9
Summary: Send test result to Mig3 service
Home-page: https://github.com/mverteuil/mig3-client
License: MIT
Keywords: python3,migration-tool,mig3
Author: Matthew de Verteuil
Author-email: onceuponajooks@gmail.com
Requires-Python: >=2.7, !=3.0.*, !=3.1.*, !=3.2.*, !=3.3.*, !=3.4.*, !=3.5.*
Classifier: Development Status :: 4 - Beta
Classifier: Environment :: Console
Classifier: Intended Audience :: Developers
Classifier: Intended Audience :: System Administrators
Classifier: License :: OSI Approved :: MIT License
Classifier: Operating System :: MacOS
Classifier: Operating System :: POSIX :: Linux
Classifier: Operating System :: Unix
Classifier: Programming Language :: Python :: 2
Classifier: Programming Language :: Python :: 3
Classifier: Programming Language :: Python :: 3.6
Classifier: Programming Language :: Python :: 3.7
Classifier: Topic :: Software Development
Classifier: Topic :: System
Classifier: Topic :: Terminals
Requires-Dist: click (>=7.0,<8.0)
Requires-Dist: gitpython (>=2.1,<3.0)
Requires-Dist: pathlib2 (>=2.3,<3.0)
Requires-Dist: pytest (<5)
Requires-Dist: pytest-json (>=0.4.0,<0.5.0)
Requires-Dist: requests (>=2.21,<3.0)
Requires-Dist: tomlkit (>=0.5.3,<0.6.0)
Project-URL: Repository, https://github.com/mverteuil/mig3-client
